NewsArticlesScraper/ArticleUrlSrapers.py
NewsArticlesScraper/Scrapers.py
NewsArticlesScraper/__init__.py
NewsArticlesScraper/test.py
NewsArticlesScraper-0.2.7.6.dist-info/METADATA
NewsArticlesScraper-0.2.7.6.dist-info/WHEEL
NewsArticlesScraper-0.2.7.6.dist-info/top_level.txt
NewsArticlesScraper-0.2.7.6.dist-info/RECORD
