Metadata-Version: 2.1
Name: NewsArticlesScraper
Version: 0.2.7.6
Summary: Scraping news articles
Author: PySlayer (Paul Antweiler)
Author-email: antweiler.paul@gmail.com
Keywords: python,news,scraping,news scraping,news articles
Classifier: Development Status :: 1 - Planning
Classifier: Intended Audience :: Developers
Classifier: Programming Language :: Python :: 3
Classifier: Operating System :: Unix
Classifier: Operating System :: MacOS :: MacOS X
Classifier: Operating System :: Microsoft :: Windows
Requires-Dist: scrapy
Requires-Dist: ciso8601
Requires-Dist: pytz
Requires-Dist: scrapy-user-agents
